torchsystem/__init__.py
torchsystem/compiler.py
torchsystem/depends.py
torchsystem/domain/__init__.py
torchsystem/domain/aggregate.py
torchsystem/domain/events.py
torchsystem/registry/__init__.py
torchsystem/registry/accessors.py
torchsystem/registry/core.py
torchsystem/services/__init__.py
torchsystem/services/prodcon.py
torchsystem/services/pubsub.py
torchsystem/services/service.py
torchsystem-1.4.6.dist-info/METADATA
torchsystem-1.4.6.dist-info/WHEEL
torchsystem-1.4.6.dist-info/licenses/LICENSE
torchsystem-1.4.6.dist-info/RECORD
