Metadata-Version: 2.4
Name: torchsystem
Version: 1.4.6
Summary: A framework for creating message-driven machine learning systems with PyTorch
License: Apache-2.0
License-File: LICENSE
Author: Eric Hermosis
Author-email: eric.hermosis@gmail.com
Requires-Python: >=3.12,<4.0
Classifier: License :: OSI Approved :: Apache Software License
Classifier: Programming Language :: Python :: 3
Classifier: Programming Language :: Python :: 3.12
Classifier: Programming Language :: Python :: 3.13
Classifier: Programming Language :: Python :: 3.14
